tests/__init__.py
tests/test_winregmgr.py
winregmgr/__init__.py
winregmgr/winreg_manager.py
winregmgr_pkg/__init__.py
winregmgr_pkg/winreg_manager.py
winregmgr-0.1.1.dist-info/LICENSE
winregmgr-0.1.1.dist-info/METADATA
winregmgr-0.1.1.dist-info/WHEEL
winregmgr-0.1.1.dist-info/top_level.txt
winregmgr-0.1.1.dist-info/RECORD
