Metadata-Version: 2.1
Name: winregmgr
Version: 0.1.1
Summary: Context manager for Windows Registry manipulations
Home-page: https://github.com/LuckyKarter/winregmgr
Author: Egor Wexler
Author-email: egor.wexler@icloud.com
License: UNKNOWN
Project-URL: Bug Tracker, https://github.com/LuckyKarter/winregmgr/issues
Platform: UNKNOWN
Classifier: Programming Language :: Python :: 3
Classifier: Intended Audience :: Developers
Classifier: License :: OSI Approved :: MIT License
Classifier: Operating System :: Microsoft :: Windows
Requires-Python: >=3.6
